wowool/apps/infobox/__init__.py
wowool/apps/infobox/config.py
wowool/infobox/__init__.py
wowool/infobox/__main__.py
wowool/infobox/app_id.py
wowool/infobox/config.py
wowool/infobox/console.py
wowool/infobox/exceptions.py
wowool/infobox/infobox.py
wowool/infobox/logger.py
wowool/infobox/session.py
wowool/infobox/utilities.py
wowool/infobox/wikidata.py.dnu
wowool/infobox/wikipedia.py
wowool/infobox/process/discovery.py
wowool/infobox/process/discovery_client.py
wowool/infobox/process/process.py
wowool_infobox-1.2.0.dist-info/METADATA
wowool_infobox-1.2.0.dist-info/WHEEL
wowool_infobox-1.2.0.dist-info/entry_points.txt
wowool_infobox-1.2.0.dist-info/top_level.txt
wowool_infobox-1.2.0.dist-info/RECORD
