Metadata-Version: 2.4
Name: wowool-infobox
Version: 1.2.0
Summary: Wowool Infobox
Home-page: https://www.wowool.com/
Author: Wowool
Author-email: info@wowool.com
Requires-Python: >=3.11
Requires-Dist: beautifulsoup4
Requires-Dist: html5lib
Requires-Dist: SQLAlchemy
Dynamic: author
Dynamic: author-email
Dynamic: description
Dynamic: description-content-type
Dynamic: home-page
Dynamic: requires-dist
Dynamic: requires-python
Dynamic: summary
